gradio_calendar/__init__.py
gradio_calendar/calendar.py
gradio_calendar/calendar.pyi
gradio_calendar/templates/component/index.js
gradio_calendar/templates/component/style.css
gradio_calendar/templates/example/index.js
gradio_calendar/templates/example/style.css
gradio_calendar-0.0.5.dist-info/METADATA
gradio_calendar-0.0.5.dist-info/WHEEL
gradio_calendar-0.0.5.dist-info/licenses/LICENSE
gradio_calendar-0.0.5.dist-info/RECORD
