Metadata-Version: 2.3
Name: gradio_calendar
Version: 0.0.5
Summary: Gradio component for selecting dates with a calendar 📆
Project-URL: repository, https://github.com/freddyaboulton/gradio-calendar
Project-URL: space, https://huggingface.co/spaces/freddyaboulton/gradio_calendar
Author-email: YOUR NAME <YOUREMAIL@domain.com>
License-Expression: MIT
License-File: LICENSE
Keywords: calendar,forms,gradio-custom-component,gradio-template-Fallback,time
Classifier: Development Status :: 3 - Alpha
Classifier: License :: OSI Approved :: Apache Software License
Classifier: Operating System :: OS Independent
Classifier: Programming Language :: Python :: 3
Classifier: Programming Language :: Python :: 3 :: Only
Classifier: Programming Language :: Python :: 3.8
Classifier: Programming Language :: Python :: 3.9
Classifier: Programming Language :: Python :: 3.10
Classifier: Programming Language :: Python :: 3.11
Classifier: Topic :: Scientific/Engineering
Classifier: Topic :: Scientific/Engineering :: Artificial Intelligence
Classifier: Topic :: Scientific/Engineering :: Visualization
Requires-Python: >=3.8
Requires-Dist: gradio<5.0,>=4.0
Provides-Extra: dev
Requires-Dist: build; extra == 'dev'
Requires-Dist: twine; extra == 'dev'
